Busanstore/Busanstore.py
Busanstore/data/NanumBarunGothicLight.ttf
Busanstore/data/busan.csv
Busanstore-0.0.8.dist-info/METADATA
Busanstore-0.0.8.dist-info/WHEEL
Busanstore-0.0.8.dist-info/top_level.txt
Busanstore-0.0.8.dist-info/RECORD
