Metadata-Version: 2.1
Name: Busanstore
Version: 0.0.8
Summary: Busan_store_data_package
Home-page: https://github.com/Dayy9984/busanmarket
Download-URL: https://github.com/Dayy9984/busanmarket
Author: dayy9984
Classifier: Programming Language :: Python :: 3
